viktor/__init__.py
viktor/__init__.pyi
viktor/__version__.py
viktor/__version__.pyi
viktor/_testing.py
viktor/_testing.pyi
viktor/api_v1.cpython-313-x86_64-linux-gnu.so
viktor/api_v1.pyi
viktor/core.cpython-313-x86_64-linux-gnu.so
viktor/core.pyi
viktor/errors.cpython-313-x86_64-linux-gnu.so
viktor/errors.pyi
viktor/geo.cpython-313-x86_64-linux-gnu.so
viktor/geo.pyi
viktor/geometry.cpython-313-x86_64-linux-gnu.so
viktor/geometry.pyi
viktor/parametrization.cpython-313-x86_64-linux-gnu.so
viktor/parametrization.pyi
viktor/result.cpython-313-x86_64-linux-gnu.so
viktor/result.pyi
viktor/testing.cpython-313-x86_64-linux-gnu.so
viktor/testing.pyi
viktor/utils.cpython-313-x86_64-linux-gnu.so
viktor/utils.pyi
viktor/views.cpython-313-x86_64-linux-gnu.so
viktor/views.pyi
viktor/_codemod/__init__.py
viktor/_codemod/__init__.pyi
viktor/_codemod/__main__.py
viktor/_codemod/__main__.pyi
viktor/_codemod/helpers.py
viktor/_codemod/helpers.pyi
viktor/_codemod/modifiers/U76.py
viktor/_codemod/modifiers/U76.pyi
viktor/_codemod/modifiers/U77.py
viktor/_codemod/modifiers/U77.pyi
viktor/_codemod/modifiers/U78.py
viktor/_codemod/modifiers/U78.pyi
viktor/_codemod/modifiers/U79.py
viktor/_codemod/modifiers/U79.pyi
viktor/_codemod/modifiers/U80.py
viktor/_codemod/modifiers/U80.pyi
viktor/_codemod/modifiers/U81.py
viktor/_codemod/modifiers/U81.pyi
viktor/_codemod/modifiers/U82.py
viktor/_codemod/modifiers/U82.pyi
viktor/_codemod/modifiers/U83.py
viktor/_codemod/modifiers/U83.pyi
viktor/_codemod/modifiers/U84.py
viktor/_codemod/modifiers/U84.pyi
viktor/_codemod/modifiers/U87.py
viktor/_codemod/modifiers/U87.pyi
viktor/_codemod/modifiers/U88.py
viktor/_codemod/modifiers/U88.pyi
viktor/_codemod/modifiers/U90.py
viktor/_codemod/modifiers/U90.pyi
viktor/_codemod/modifiers/__init__.py
viktor/_codemod/modifiers/__init__.pyi
viktor/_vendor/__init__.py
viktor/_vendor/_yaml_ft/__init__.py
viktor/_vendor/bin/filetype
viktor/_vendor/bin/trimesh
viktor/_vendor/certifi/__init__.py
viktor/_vendor/certifi-2026.1.4.dist-info/licenses/LICENSE
viktor/_vendor/charset_normalizer-3.4.4.dist-info/licenses/LICENSE
viktor/_vendor/idna-3.11.dist-info/licenses/LICENSE.md
viktor/_vendor/libcst-1.8.6.dist-info/licenses/LICENSE
viktor/_vendor/pyyaml_ft-8.0.0.dist-info/licenses/LICENSE
viktor/_vendor/requests-2.32.5.dist-info/licenses/LICENSE
viktor/_vendor/trimesh-4.9.0.dist-info/licenses/LICENSE.md
viktor/_vendor/urllib3-2.6.3.dist-info/licenses/LICENSE.txt
viktor-14.27.0.dist-info/licenses/LICENSE.txt
viktor-14.27.0.dist-info/METADATA
viktor-14.27.0.dist-info/WHEEL
viktor-14.27.0.dist-info/top_level.txt
viktor/_vendor/certifi-2026.1.4.dist-info/INSTALLER
viktor/_vendor/certifi-2026.1.4.dist-info/METADATA
viktor/_vendor/certifi-2026.1.4.dist-info/RECORD
viktor/_vendor/certifi-2026.1.4.dist-info/WHEEL
viktor/_vendor/certifi-2026.1.4.dist-info/top_level.txt
viktor/_vendor/charset_normalizer-3.4.4.dist-info/INSTALLER
viktor/_vendor/charset_normalizer-3.4.4.dist-info/METADATA
viktor/_vendor/charset_normalizer-3.4.4.dist-info/RECORD
viktor/_vendor/charset_normalizer-3.4.4.dist-info/WHEEL
viktor/_vendor/charset_normalizer-3.4.4.dist-info/entry_points.txt
viktor/_vendor/charset_normalizer-3.4.4.dist-info/top_level.txt
viktor/_vendor/filetype-1.2.0.dist-info/INSTALLER
viktor/_vendor/filetype-1.2.0.dist-info/LICENSE
viktor/_vendor/filetype-1.2.0.dist-info/METADATA
viktor/_vendor/filetype-1.2.0.dist-info/RECORD
viktor/_vendor/filetype-1.2.0.dist-info/REQUESTED
viktor/_vendor/filetype-1.2.0.dist-info/WHEEL
viktor/_vendor/filetype-1.2.0.dist-info/entry_points.txt
viktor/_vendor/filetype-1.2.0.dist-info/top_level.txt
viktor/_vendor/filetype-1.2.0.dist-info/zip-safe
viktor/_vendor/idna-3.11.dist-info/INSTALLER
viktor/_vendor/idna-3.11.dist-info/METADATA
viktor/_vendor/idna-3.11.dist-info/RECORD
viktor/_vendor/idna-3.11.dist-info/WHEEL
viktor/_vendor/libcst-1.8.6.dist-info/INSTALLER
viktor/_vendor/libcst-1.8.6.dist-info/METADATA
viktor/_vendor/libcst-1.8.6.dist-info/RECORD
viktor/_vendor/libcst-1.8.6.dist-info/REQUESTED
viktor/_vendor/libcst-1.8.6.dist-info/WHEEL
viktor/_vendor/libcst-1.8.6.dist-info/top_level.txt
viktor/_vendor/pyyaml_ft-8.0.0.dist-info/INSTALLER
viktor/_vendor/pyyaml_ft-8.0.0.dist-info/METADATA
viktor/_vendor/pyyaml_ft-8.0.0.dist-info/RECORD
viktor/_vendor/pyyaml_ft-8.0.0.dist-info/WHEEL
viktor/_vendor/pyyaml_ft-8.0.0.dist-info/top_level.txt
viktor/_vendor/requests-2.32.5.dist-info/INSTALLER
viktor/_vendor/requests-2.32.5.dist-info/METADATA
viktor/_vendor/requests-2.32.5.dist-info/RECORD
viktor/_vendor/requests-2.32.5.dist-info/REQUESTED
viktor/_vendor/requests-2.32.5.dist-info/WHEEL
viktor/_vendor/requests-2.32.5.dist-info/top_level.txt
viktor/_vendor/requests_toolbelt-1.0.0.dist-info/AUTHORS.rst
viktor/_vendor/requests_toolbelt-1.0.0.dist-info/INSTALLER
viktor/_vendor/requests_toolbelt-1.0.0.dist-info/LICENSE
viktor/_vendor/requests_toolbelt-1.0.0.dist-info/METADATA
viktor/_vendor/requests_toolbelt-1.0.0.dist-info/RECORD
viktor/_vendor/requests_toolbelt-1.0.0.dist-info/REQUESTED
viktor/_vendor/requests_toolbelt-1.0.0.dist-info/WHEEL
viktor/_vendor/requests_toolbelt-1.0.0.dist-info/top_level.txt
viktor/_vendor/tomli-2.0.1.dist-info/INSTALLER
viktor/_vendor/tomli-2.0.1.dist-info/LICENSE
viktor/_vendor/tomli-2.0.1.dist-info/METADATA
viktor/_vendor/tomli-2.0.1.dist-info/RECORD
viktor/_vendor/tomli-2.0.1.dist-info/REQUESTED
viktor/_vendor/tomli-2.0.1.dist-info/WHEEL
viktor/_vendor/tomli_w-1.2.0.dist-info/INSTALLER
viktor/_vendor/tomli_w-1.2.0.dist-info/LICENSE
viktor/_vendor/tomli_w-1.2.0.dist-info/METADATA
viktor/_vendor/tomli_w-1.2.0.dist-info/RECORD
viktor/_vendor/tomli_w-1.2.0.dist-info/REQUESTED
viktor/_vendor/tomli_w-1.2.0.dist-info/WHEEL
viktor/_vendor/trimesh-4.9.0.dist-info/INSTALLER
viktor/_vendor/trimesh-4.9.0.dist-info/METADATA
viktor/_vendor/trimesh-4.9.0.dist-info/RECORD
viktor/_vendor/trimesh-4.9.0.dist-info/REQUESTED
viktor/_vendor/trimesh-4.9.0.dist-info/WHEEL
viktor/_vendor/trimesh-4.9.0.dist-info/entry_points.txt
