Metadata-Version: 2.1
Name: viktor
Version: 14.27.0
Summary: SDK for building a VIKTOR application
Home-page: https://www.viktor.ai/
Author: VIKTOR
Author-email: support@viktor.ai
License: see LICENSE.txt
Project-URL: Apps Gallery, https://www.viktor.ai/apps-gallery
Project-URL: Community, https://community.viktor.ai/
Project-URL: Documentation, https://docs.viktor.ai/docs/welcome
Project-URL: Release notes, https://docs.viktor.ai/sdk/changelog
Classifier: Environment :: Web Environment
Classifier: Intended Audience :: Developers
Classifier: License :: Free To Use But Restricted
Classifier: Operating System :: Microsoft :: Windows
Classifier: Operating System :: POSIX :: Linux
Classifier: Programming Language :: Python :: 3.10
Classifier: Programming Language :: Python :: 3.11
Classifier: Programming Language :: Python :: 3.12
Classifier: Programming Language :: Python :: 3.13
Classifier: Programming Language :: Python :: 3.14
License-File: LICENSE.txt
Requires-Dist: munch>=2.5.0
Requires-Dist: pandas>=0.23.4
Requires-Dist: matplotlib!=3.9.0,>=2.2.2
Requires-Dist: numpy>=1.15.0; python_version < "3.13"
Requires-Dist: numpy>=1.26.0; python_version >= "3.13"
